app/__init__.py
app/trifledb.py
app/trifledb_server.py
tests/__init__.py
tests/test_trifledb_server.py
trifledb-0.1.1.dev0.dist-info/LICENSE
trifledb-0.1.1.dev0.dist-info/METADATA
trifledb-0.1.1.dev0.dist-info/WHEEL
trifledb-0.1.1.dev0.dist-info/top_level.txt
trifledb-0.1.1.dev0.dist-info/RECORD
